aiida_abacus/__init__.py
aiida_abacus/calculations.py
aiida_abacus/cli.py
aiida_abacus/helpers.py
aiida_abacus/common/__init__.py
aiida_abacus/common/opthold.py
aiida_abacus/common/sumo_kpath.py
aiida_abacus/data/__init__.py
aiida_abacus/data/orbital.py
aiida_abacus/group/__init__.py
aiida_abacus/group/orb_group.py
aiida_abacus/parsers/__init__.py
aiida_abacus/parsers/abacus.py
aiida_abacus/parsers/raw_parsers.py
aiida_abacus/protocols/band.yaml
aiida_abacus/protocols/base.yaml
aiida_abacus/protocols/relax.yaml
aiida_abacus/workflows/__init__.py
aiida_abacus/workflows/band.py
aiida_abacus/workflows/base.py
aiida_abacus/workflows/relax.py
aiida_abacus-0.3.1.dist-info/METADATA
aiida_abacus-0.3.1.dist-info/WHEEL
aiida_abacus-0.3.1.dist-info/entry_points.txt
aiida_abacus-0.3.1.dist-info/licenses/LICENSE
aiida_abacus-0.3.1.dist-info/RECORD
