Metadata-Version: 2.4
Name: aiida-abacus
Version: 0.3.1
Summary: AiiDA plugin for ABACUS
Project-URL: Source, https://github.com/MCresearch/aiida-abacus
Author: aiida-abacus team
License: MIT License
License-File: LICENSE
Keywords: aiida,plugin
Classifier: Development Status :: 3 - Alpha
Classifier: Framework :: AiiDA
Classifier: Intended Audience :: Science/Research
Classifier: License :: OSI Approved :: MIT License
Classifier: Natural Language :: English
Classifier: Programming Language :: Python
Requires-Python: >=3.10
Requires-Dist: aiida-core<3,>=2.5
Requires-Dist: aiida-pseudo~=1.7.2
Requires-Dist: ase
Requires-Dist: pydantic
Requires-Dist: tqdm
Requires-Dist: voluptuous
Provides-Extra: dev
Requires-Dist: ruff>=0.12.12; extra == 'dev'
Provides-Extra: docs
Requires-Dist: furo; extra == 'docs'
Requires-Dist: markupsafe>=2.1.1; extra == 'docs'
Requires-Dist: myst-parser~=3.0.0; extra == 'docs'
Requires-Dist: sphinx-autoapi~=3.0.0; extra == 'docs'
Requires-Dist: sphinx-book-theme~=1.0.1; extra == 'docs'
Requires-Dist: sphinx-click~=4.4.0; extra == 'docs'
Requires-Dist: sphinx-copybutton~=0.5.2; extra == 'docs'
Requires-Dist: sphinx-design~=0.6.1; extra == 'docs'
Requires-Dist: sphinxcontrib-contentui; extra == 'docs'
Requires-Dist: sphinxcontrib-details-directive~=0.1.0; extra == 'docs'
Requires-Dist: sphinxemoji; extra == 'docs'
Requires-Dist: sphinx~=6.2.1; extra == 'docs'
Provides-Extra: pre-commit
Requires-Dist: hatch; extra == 'pre-commit'
Requires-Dist: pre-commit~=3.5; extra == 'pre-commit'
Provides-Extra: tutorial
Requires-Dist: aiida-vasp; extra == 'tutorial'
Requires-Dist: ase-weas-widget; extra == 'tutorial'
Requires-Dist: pymatgen; extra == 'tutorial'
Requires-Dist: sumo; extra == 'tutorial'
